nolog/__init__.py
nolog/logic_engine/__init__.py
nolog/logic_engine/conjunction.py
nolog/logic_engine/disjunction.py
nolog/logic_engine/negation.py
nolog/logic_engine/predicate.py
nolog/tests/__init__.py
nolog/tests/conftest.py
nolog/tests/test_conjunction.py
nolog/tests/test_disjunction.py
nolog/tests/test_negation.py
nolog/tests/test_predicate.py
nolog-0.1.3.dist-info/LICENSE
nolog-0.1.3.dist-info/WHEEL
nolog-0.1.3.dist-info/METADATA
nolog-0.1.3.dist-info/RECORD
