Metadata-Version: 2.1
Name: nolog
Version: 0.1.3
Summary: A native Logic engine for Python
License: MIT
Author: Dragos Dumitrache
Author-email: dragos@afterburner.dev
Requires-Python: >=3.10,<4.0
Classifier: License :: OSI Approved :: MIT License
Classifier: Programming Language :: Python :: 3
Classifier: Programming Language :: Python :: 3.10
Classifier: Programming Language :: Python :: 3.11
